pyreadcon/__about__.py
pyreadcon/__init__.py
pyreadcon-0.0.1.dist-info/METADATA
pyreadcon-0.0.1.dist-info/WHEEL
pyreadcon-0.0.1.dist-info/licenses/LICENSE.txt
pyreadcon-0.0.1.dist-info/RECORD
